{
  "paper_doi": "local/Deep_dip_teardown_of_tubeless_insulin_pump",
  "paper_title": "Deep dip teardown of tubeless insulin pump",
  "concepts": [
    {
      "text": "pod",
      "frequency": 56,
      "relevance_score": 0.9218373936014088,
      "source_papers": [
        "local/Deep_dip_teardown_of_tubeless_insulin_pump"
      ],
      "source_domain": "medical_device_cybersecurity",
      "extraction_method": "tfidf",
      "created_at": "2025-08-07T16:13:36.003007+00:00",
      "synonyms": []
    },
    {
      "text": "insulin",
      "frequency": 42,
      "relevance_score": 0.7163780452010566,
      "source_papers": [
        "local/Deep_dip_teardown_of_tubeless_insulin_pump"
      ],
      "source_domain": "medical_device_cybersecurity",
      "extraction_method": "tfidf",
      "created_at": "2025-08-07T16:13:35.965928+00:00",
      "synonyms": []
    },
    {
      "text": "chip",
      "frequency": 35,
      "relevance_score": 0.6136483710008804,
      "source_papers": [
        "local/Deep_dip_teardown_of_tubeless_insulin_pump"
      ],
      "source_domain": "medical_device_cybersecurity",
      "extraction_method": "tfidf",
      "created_at": "2025-08-07T16:13:36.028174+00:00",
      "synonyms": []
    },
    {
      "text": "backside de -processing",
      "frequency": 2,
      "relevance_score": 0.5793513354857646,
      "source_papers": [
        "local/Deep_dip_teardown_of_tubeless_insulin_pump"
      ],
      "source_domain": "medical_device_cybersecurity",
      "extraction_method": "tfidf",
      "created_at": "2025-08-07T16:13:36.135055+00:00",
      "synonyms": []
    },
    {
      "text": "0v 0",
      "frequency": 18,
      "relevance_score": 0.5641620193718815,
      "source_papers": [
        "local/Deep_dip_teardown_of_tubeless_insulin_pump"
      ],
      "source_domain": "medical_device_cybersecurity",
      "extraction_method": "tfidf",
      "created_at": "2025-08-07T16:13:36.099864+00:00",
      "synonyms": []
    },
    {
      "text": "tp 0v 0",
      "frequency": 11,
      "relevance_score": 0.5614323451717053,
      "source_papers": [
        "local/Deep_dip_teardown_of_tubeless_insulin_pump"
      ],
      "source_domain": "medical_device_cybersecurity",
      "extraction_method": "tfidf",
      "created_at": "2025-08-07T16:13:36.126734+00:00",
      "synonyms": []
    },
    {
      "text": "process",
      "frequency": 21,
      "relevance_score": 0.5581890226005284,
      "source_papers": [
        "local/Deep_dip_teardown_of_tubeless_insulin_pump"
      ],
      "source_domain": "medical_device_cybersecurity",
      "extraction_method": "tfidf",
      "created_at": "2025-08-07T16:13:35.967891+00:00",
      "synonyms": []
    },
    {
      "text": "device",
      "frequency": 30,
      "relevance_score": 0.5402700322864691,
      "source_papers": [
        "local/Deep_dip_teardown_of_tubeless_insulin_pump"
      ],
      "source_domain": "medical_device_cybersecurity",
      "extraction_method": "tfidf",
      "created_at": "2025-08-07T16:13:35.968500+00:00",
      "synonyms": []
    },
    {
      "text": "pcb",
      "frequency": 28,
      "relevance_score": 0.5109186968007045,
      "source_papers": [
        "local/Deep_dip_teardown_of_tubeless_insulin_pump"
      ],
      "source_domain": "medical_device_cybersecurity",
      "extraction_method": "tfidf",
      "created_at": "2025-08-07T16:13:36.013984+00:00",
      "synonyms": []
    },
    {
      "text": "yes yes 10",
      "frequency": 6,
      "relevance_score": 0.4880540064572938,
      "source_papers": [
        "local/Deep_dip_teardown_of_tubeless_insulin_pump"
      ],
      "source_domain": "medical_device_cybersecurity",
      "extraction_method": "tfidf",
      "created_at": "2025-08-07T16:13:36.135936+00:00",
      "synonyms": []
    },
    {
      "text": "de -processing",
      "frequency": 2,
      "relevance_score": 0.4793513354857646,
      "source_papers": [
        "local/Deep_dip_teardown_of_tubeless_insulin_pump"
      ],
      "source_domain": "medical_device_cybersecurity",
      "extraction_method": "tfidf",
      "created_at": "2025-08-07T16:13:36.113333+00:00",
      "synonyms": []
    },
    {
      "text": "insulin delivery process",
      "frequency": 2,
      "relevance_score": 0.4793513354857646,
      "source_papers": [
        "local/Deep_dip_teardown_of_tubeless_insulin_pump"
      ],
      "source_domain": "medical_device_cybersecurity",
      "extraction_method": "tfidf",
      "created_at": "2025-08-07T16:13:36.124580+00:00",
      "synonyms": []
    },
    {
      "text": "tp 0v",
      "frequency": 11,
      "relevance_score": 0.4614323451717053,
      "source_papers": [
        "local/Deep_dip_teardown_of_tubeless_insulin_pump"
      ],
      "source_domain": "medical_device_cybersecurity",
      "extraction_method": "tfidf",
      "created_at": "2025-08-07T16:13:36.099667+00:00",
      "synonyms": []
    },
    {
      "text": "0v 0 732",
      "frequency": 4,
      "relevance_score": 0.45870267097152917,
      "source_papers": [
        "local/Deep_dip_teardown_of_tubeless_insulin_pump"
      ],
      "source_domain": "medical_device_cybersecurity",
      "extraction_method": "tfidf",
      "created_at": "2025-08-07T16:13:36.126954+00:00",
      "synonyms": []
    },
    {
      "text": "0 732 0",
      "frequency": 4,
      "relevance_score": 0.45870267097152917,
      "source_papers": [
        "local/Deep_dip_teardown_of_tubeless_insulin_pump"
      ],
      "source_domain": "medical_device_cybersecurity",
      "extraction_method": "tfidf",
      "created_at": "2025-08-07T16:13:36.127161+00:00",
      "synonyms": []
    },
    {
      "text": "2 87v 0",
      "frequency": 4,
      "relevance_score": 0.45870267097152917,
      "source_papers": [
        "local/Deep_dip_teardown_of_tubeless_insulin_pump"
      ],
      "source_domain": "medical_device_cybersecurity",
      "extraction_method": "tfidf",
      "created_at": "2025-08-07T16:13:36.128972+00:00",
      "synonyms": []
    },
    {
      "text": "gnd 0v gnd",
      "frequency": 4,
      "relevance_score": 0.45870267097152917,
      "source_papers": [
        "local/Deep_dip_teardown_of_tubeless_insulin_pump"
      ],
      "source_domain": "medical_device_cybersecurity",
      "extraction_method": "tfidf",
      "created_at": "2025-08-07T16:13:36.130060+00:00",
      "synonyms": []
    },
    {
      "text": "0v gnd 0",
      "frequency": 4,
      "relevance_score": 0.45870267097152917,
      "source_papers": [
        "local/Deep_dip_teardown_of_tubeless_insulin_pump"
      ],
      "source_domain": "medical_device_cybersecurity",
      "extraction_method": "tfidf",
      "created_at": "2025-08-07T16:13:36.130274+00:00",
      "synonyms": []
    },
    {
      "text": "0v 0 686",
      "frequency": 4,
      "relevance_score": 0.45870267097152917,
      "source_papers": [
        "local/Deep_dip_teardown_of_tubeless_insulin_pump"
      ],
      "source_domain": "medical_device_cybersecurity",
      "extraction_method": "tfidf",
      "created_at": "2025-08-07T16:13:36.131069+00:00",
      "synonyms": []
    },
    {
      "text": "0 686 n",
      "frequency": 4,
      "relevance_score": 0.45870267097152917,
      "source_papers": [
        "local/Deep_dip_teardown_of_tubeless_insulin_pump"
      ],
      "source_domain": "medical_device_cybersecurity",
      "extraction_method": "tfidf",
      "created_at": "2025-08-07T16:13:36.131281+00:00",
      "synonyms": []
    },
    {
      "text": "firmware",
      "frequency": 24,
      "relevance_score": 0.4522160258291752,
      "source_papers": [
        "local/Deep_dip_teardown_of_tubeless_insulin_pump"
      ],
      "source_domain": "medical_device_cybersecurity",
      "extraction_method": "tfidf",
      "created_at": "2025-08-07T16:13:35.971239+00:00",
      "synonyms": []
    },
    {
      "text": "yes",
      "frequency": 24,
      "relevance_score": 0.4522160258291752,
      "source_papers": [
        "local/Deep_dip_teardown_of_tubeless_insulin_pump"
      ],
      "source_domain": "medical_device_cybersecurity",
      "extraction_method": "tfidf",
      "created_at": "2025-08-07T16:13:36.031112+00:00",
      "synonyms": []
    },
    {
      "text": "pod sc9s08er48chp 2n80a",
      "frequency": 3,
      "relevance_score": 0.44402700322864685,
      "source_papers": [
        "local/Deep_dip_teardown_of_tubeless_insulin_pump"
      ],
      "source_domain": "medical_device_cybersecurity",
      "extraction_method": "tfidf",
      "created_at": "2025-08-07T16:13:36.125166+00:00",
      "synonyms": []
    },
    {
      "text": "pad tp 0",
      "frequency": 3,
      "relevance_score": 0.44402700322864685,
      "source_papers": [
        "local/Deep_dip_teardown_of_tubeless_insulin_pump"
      ],
      "source_domain": "medical_device_cybersecurity",
      "extraction_method": "tfidf",
      "created_at": "2025-08-07T16:13:36.125555+00:00",
      "synonyms": []
    },
    {
      "text": "tp 0 2",
      "frequency": 3,
      "relevance_score": 0.44402700322864685,
      "source_papers": [
        "local/Deep_dip_teardown_of_tubeless_insulin_pump"
      ],
      "source_domain": "medical_device_cybersecurity",
      "extraction_method": "tfidf",
      "created_at": "2025-08-07T16:13:36.125749+00:00",
      "synonyms": []
    },
    {
      "text": "0 2 04",
      "frequency": 3,
      "relevance_score": 0.44402700322864685,
      "source_papers": [
        "local/Deep_dip_teardown_of_tubeless_insulin_pump"
      ],
      "source_domain": "medical_device_cybersecurity",
      "extraction_method": "tfidf",
      "created_at": "2025-08-07T16:13:36.125943+00:00",
      "synonyms": []
    },
    {
      "text": "2 04 v",
      "frequency": 3,
      "relevance_score": 0.44402700322864685,
      "source_papers": [
        "local/Deep_dip_teardown_of_tubeless_insulin_pump"
      ],
      "source_domain": "medical_device_cybersecurity",
      "extraction_method": "tfidf",
      "created_at": "2025-08-07T16:13:36.126137+00:00",
      "synonyms": []
    },
    {
      "text": "04 v 0",
      "frequency": 3,
      "relevance_score": 0.44402700322864685,
      "source_papers": [
        "local/Deep_dip_teardown_of_tubeless_insulin_pump"
      ],
      "source_domain": "medical_device_cybersecurity",
      "extraction_method": "tfidf",
      "created_at": "2025-08-07T16:13:36.126333+00:00",
      "synonyms": []
    },
    {
      "text": "0v 0 731",
      "frequency": 3,
      "relevance_score": 0.44402700322864685,
      "source_papers": [
        "local/Deep_dip_teardown_of_tubeless_insulin_pump"
      ],
      "source_domain": "medical_device_cybersecurity",
      "extraction_method": "tfidf",
      "created_at": "2025-08-07T16:13:36.127355+00:00",
      "synonyms": []
    },
    {
      "text": "0 731 0",
      "frequency": 3,
      "relevance_score": 0.44402700322864685,
      "source_papers": [
        "local/Deep_dip_teardown_of_tubeless_insulin_pump"
      ],
      "source_domain": "medical_device_cybersecurity",
      "extraction_method": "tfidf",
      "created_at": "2025-08-07T16:13:36.127550+00:00",
      "synonyms": []
    },
    {
      "text": "731 0 731",
      "frequency": 3,
      "relevance_score": 0.44402700322864685,
      "source_papers": [
        "local/Deep_dip_teardown_of_tubeless_insulin_pump"
      ],
      "source_domain": "medical_device_cybersecurity",
      "extraction_method": "tfidf",
      "created_at": "2025-08-07T16:13:36.127744+00:00",
      "synonyms": []
    },
    {
      "text": "0 734 0",
      "frequency": 3,
      "relevance_score": 0.44402700322864685,
      "source_papers": [
        "local/Deep_dip_teardown_of_tubeless_insulin_pump"
      ],
      "source_domain": "medical_device_cybersecurity",
      "extraction_method": "tfidf",
      "created_at": "2025-08-07T16:13:36.134052+00:00",
      "synonyms": []
    },
    {
      "text": "2010 yes yes",
      "frequency": 3,
      "relevance_score": 0.44402700322864685,
      "source_papers": [
        "local/Deep_dip_teardown_of_tubeless_insulin_pump"
      ],
      "source_domain": "medical_device_cybersecurity",
      "extraction_method": "tfidf",
      "created_at": "2025-08-07T16:13:36.135504+00:00",
      "synonyms": []
    },
    {
      "text": "1f 03 9c",
      "frequency": 3,
      "relevance_score": 0.44402700322864685,
      "source_papers": [
        "local/Deep_dip_teardown_of_tubeless_insulin_pump"
      ],
      "source_domain": "medical_device_cybersecurity",
      "extraction_method": "tfidf",
      "created_at": "2025-08-07T16:13:36.137337+00:00",
      "synonyms": []
    },
    {
      "text": "ff 00 09",
      "frequency": 3,
      "relevance_score": 0.44402700322864685,
      "source_papers": [
        "local/Deep_dip_teardown_of_tubeless_insulin_pump"
      ],
      "source_domain": "medical_device_cybersecurity",
      "extraction_method": "tfidf",
      "created_at": "2025-08-07T16:13:36.137550+00:00",
      "synonyms": []
    },
    {
      "text": "00 09 07",
      "frequency": 3,
      "relevance_score": 0.44402700322864685,
      "source_papers": [
        "local/Deep_dip_teardown_of_tubeless_insulin_pump"
      ],
      "source_domain": "medical_device_cybersecurity",
      "extraction_method": "tfidf",
      "created_at": "2025-08-07T16:13:36.137746+00:00",
      "synonyms": []
    },
    {
      "text": "09 07 11",
      "frequency": 3,
      "relevance_score": 0.44402700322864685,
      "source_papers": [
        "local/Deep_dip_teardown_of_tubeless_insulin_pump"
      ],
      "source_domain": "medical_device_cybersecurity",
      "extraction_method": "tfidf",
      "created_at": "2025-08-07T16:13:36.137945+00:00",
      "synonyms": []
    },
    {
      "text": "teardown process",
      "frequency": 6,
      "relevance_score": 0.43805400645729387,
      "source_papers": [
        "local/Deep_dip_teardown_of_tubeless_insulin_pump"
      ],
      "source_domain": "medical_device_cybersecurity",
      "extraction_method": "tfidf",
      "created_at": "2025-08-07T16:13:36.081318+00:00",
      "synonyms": []
    },
    {
      "text": "were",
      "frequency": 23,
      "relevance_score": 0.4375403580862929,
      "source_papers": [
        "local/Deep_dip_teardown_of_tubeless_insulin_pump"
      ],
      "source_domain": "medical_device_cybersecurity",
      "extraction_method": "tfidf",
      "created_at": "2025-08-07T16:13:35.981629+00:00",
      "synonyms": []
    },
    {
      "text": "insulin pump",
      "frequency": 16,
      "relevance_score": 0.4348106838861168,
      "source_papers": [
        "local/Deep_dip_teardown_of_tubeless_insulin_pump"
      ],
      "source_domain": "medical_device_cybersecurity",
      "extraction_method": "tfidf",
      "created_at": "2025-08-07T16:13:36.080685+00:00",
      "synonyms": []
    },
    {
      "text": "tubeless insulin pump",
      "frequency": 9,
      "relevance_score": 0.4320810096859407,
      "source_papers": [
        "local/Deep_dip_teardown_of_tubeless_insulin_pump"
      ],
      "source_domain": "medical_device_cybersecurity",
      "extraction_method": "tfidf",
      "created_at": "2025-08-07T16:13:36.123794+00:00",
      "synonyms": []
    },
    {
      "text": "0 726 0",
      "frequency": 2,
      "relevance_score": 0.42935133548576454,
      "source_papers": [
        "local/Deep_dip_teardown_of_tubeless_insulin_pump"
      ],
      "source_domain": "medical_device_cybersecurity",
      "extraction_method": "tfidf",
      "created_at": "2025-08-07T16:13:36.126534+00:00",
      "synonyms": []
    },
    {
      "text": "tp r 0v",
      "frequency": 2,
      "relevance_score": 0.42935133548576454,
      "source_papers": [
        "local/Deep_dip_teardown_of_tubeless_insulin_pump"
      ],
      "source_domain": "medical_device_cybersecurity",
      "extraction_method": "tfidf",
      "created_at": "2025-08-07T16:13:36.128133+00:00",
      "synonyms": []
    },
    {
      "text": "r 0v 0",
      "frequency": 2,
      "relevance_score": 0.42935133548576454,
      "source_papers": [
        "local/Deep_dip_teardown_of_tubeless_insulin_pump"
      ],
      "source_domain": "medical_device_cybersecurity",
      "extraction_method": "tfidf",
      "created_at": "2025-08-07T16:13:36.128327+00:00",
      "synonyms": []
    },
    {
      "text": "tp c 2",
      "frequency": 2,
      "relevance_score": 0.42935133548576454,
      "source_papers": [
        "local/Deep_dip_teardown_of_tubeless_insulin_pump"
      ],
      "source_domain": "medical_device_cybersecurity",
      "extraction_method": "tfidf",
      "created_at": "2025-08-07T16:13:36.128534+00:00",
      "synonyms": []
    },
    {
      "text": "c 2 87v",
      "frequency": 2,
      "relevance_score": 0.42935133548576454,
      "source_papers": [
        "local/Deep_dip_teardown_of_tubeless_insulin_pump"
      ],
      "source_domain": "medical_device_cybersecurity",
      "extraction_method": "tfidf",
      "created_at": "2025-08-07T16:13:36.128734+00:00",
      "synonyms": []
    },
    {
      "text": "tp battery 2",
      "frequency": 2,
      "relevance_score": 0.42935133548576454,
      "source_papers": [
        "local/Deep_dip_teardown_of_tubeless_insulin_pump"
      ],
      "source_domain": "medical_device_cybersecurity",
      "extraction_method": "tfidf",
      "created_at": "2025-08-07T16:13:36.129405+00:00",
      "synonyms": []
    },
    {
      "text": "battery 2 87v",
      "frequency": 2,
      "relevance_score": 0.42935133548576454,
      "source_papers": [
        "local/Deep_dip_teardown_of_tubeless_insulin_pump"
      ],
      "source_domain": "medical_device_cybersecurity",
      "extraction_method": "tfidf",
      "created_at": "2025-08-07T16:13:36.129625+00:00",
      "synonyms": []
    },
    {
      "text": "power battery 3v",
      "frequency": 2,
      "relevance_score": 0.42935133548576454,
      "source_papers": [
        "local/Deep_dip_teardown_of_tubeless_insulin_pump"
      ],
      "source_domain": "medical_device_cybersecurity",
      "extraction_method": "tfidf",
      "created_at": "2025-08-07T16:13:36.129859+00:00",
      "synonyms": []
    },
    {
      "text": "gnd 0 353",
      "frequency": 2,
      "relevance_score": 0.42935133548576454,
      "source_papers": [
        "local/Deep_dip_teardown_of_tubeless_insulin_pump"
      ],
      "source_domain": "medical_device_cybersecurity",
      "extraction_method": "tfidf",
      "created_at": "2025-08-07T16:13:36.130471+00:00",
      "synonyms": []
    }
  ],
  "extraction_timestamp": "2025-08-07T16:13:36.139888+00:00",
  "extraction_method": "mixed",
  "total_concept_count": 50,
  "processing_metadata": {
    "strategies_used": [
      "tfidf"
    ],
    "total_concepts_found": 50,
    "concepts_after_consolidation": 50,
    "concepts_after_filtering": 50
  },
  "_metadata": {
    "saved_at": "2025-08-07T16:13:36.140068+00:00",
    "repository_version": "1.0",
    "domain": "medical_device_cybersecurity"
  }
}