{
  "paper_doi": "local/ACRIC__Securing_Legacy_Communication_Networks_via_Authenticated_Cyclic_Redundancy_Integrity_Check",
  "paper_title": "ACRIC  Securing Legacy Communication Networks via Authenticated Cyclic Redundancy Integrity Check",
  "concepts": [
    {
      "text": "acric",
      "frequency": 71,
      "relevance_score": 1.0,
      "source_papers": [
        "local/ACRIC__Securing_Legacy_Communication_Networks_via_Authenticated_Cyclic_Redundancy_Integrity_Check"
      ],
      "source_domain": "medical_device_cybersecurity",
      "extraction_method": "tfidf",
      "created_at": "2025-08-07T16:13:34.129920+00:00",
      "synonyms": []
    },
    {
      "text": "security",
      "frequency": 91,
      "relevance_score": 1.0,
      "source_papers": [
        "local/ACRIC__Securing_Legacy_Communication_Networks_via_Authenticated_Cyclic_Redundancy_Integrity_Check"
      ],
      "source_domain": "medical_device_cybersecurity",
      "extraction_method": "tfidf",
      "created_at": "2025-08-07T16:13:34.138568+00:00",
      "synonyms": []
    },
    {
      "text": "systems",
      "frequency": 51,
      "relevance_score": 0.9344718829687291,
      "source_papers": [
        "local/ACRIC__Securing_Legacy_Communication_Networks_via_Authenticated_Cyclic_Redundancy_Integrity_Check"
      ],
      "source_domain": "medical_device_cybersecurity",
      "extraction_method": "tfidf",
      "created_at": "2025-08-07T16:13:34.136299+00:00",
      "synonyms": []
    },
    {
      "text": "crc",
      "frequency": 58,
      "relevance_score": 0.8784190041605154,
      "source_papers": [
        "local/ACRIC__Securing_Legacy_Communication_Networks_via_Authenticated_Cyclic_Redundancy_Integrity_Check"
      ],
      "source_domain": "medical_device_cybersecurity",
      "extraction_method": "tfidf",
      "created_at": "2025-08-07T16:13:34.149113+00:00",
      "synonyms": []
    },
    {
      "text": "industrial",
      "frequency": 51,
      "relevance_score": 0.784471882968729,
      "source_papers": [
        "local/ACRIC__Securing_Legacy_Communication_Networks_via_Authenticated_Cyclic_Redundancy_Integrity_Check"
      ],
      "source_domain": "medical_device_cybersecurity",
      "extraction_method": "tfidf",
      "created_at": "2025-08-07T16:13:34.130753+00:00",
      "synonyms": []
    },
    {
      "text": "authentication",
      "frequency": 51,
      "relevance_score": 0.784471882968729,
      "source_papers": [
        "local/ACRIC__Securing_Legacy_Communication_Networks_via_Authenticated_Cyclic_Redundancy_Integrity_Check"
      ],
      "source_domain": "medical_device_cybersecurity",
      "extraction_method": "tfidf",
      "created_at": "2025-08-07T16:13:34.139469+00:00",
      "synonyms": []
    },
    {
      "text": "legacy",
      "frequency": 42,
      "relevance_score": 0.663682727150718,
      "source_papers": [
        "local/ACRIC__Securing_Legacy_Communication_Networks_via_Authenticated_Cyclic_Redundancy_Integrity_Check"
      ],
      "source_domain": "medical_device_cybersecurity",
      "extraction_method": "tfidf",
      "created_at": "2025-08-07T16:13:34.130455+00:00",
      "synonyms": []
    },
    {
      "text": "protocols",
      "frequency": 30,
      "relevance_score": 0.65263051939337,
      "source_papers": [
        "local/ACRIC__Securing_Legacy_Communication_Networks_via_Authenticated_Cyclic_Redundancy_Integrity_Check"
      ],
      "source_domain": "medical_device_cybersecurity",
      "extraction_method": "tfidf",
      "created_at": "2025-08-07T16:13:34.137673+00:00",
      "synonyms": []
    },
    {
      "text": "message",
      "frequency": 40,
      "relevance_score": 0.6368406925244934,
      "source_papers": [
        "local/ACRIC__Securing_Legacy_Communication_Networks_via_Authenticated_Cyclic_Redundancy_Integrity_Check"
      ],
      "source_domain": "medical_device_cybersecurity",
      "extraction_method": "tfidf",
      "created_at": "2025-08-07T16:13:34.139245+00:00",
      "synonyms": []
    },
    {
      "text": "system",
      "frequency": 28,
      "relevance_score": 0.6257884847671453,
      "source_papers": [
        "local/ACRIC__Securing_Legacy_Communication_Networks_via_Authenticated_Cyclic_Redundancy_Integrity_Check"
      ],
      "source_domain": "medical_device_cybersecurity",
      "extraction_method": "tfidf",
      "created_at": "2025-08-07T16:13:34.140675+00:00",
      "synonyms": []
    },
    {
      "text": "com- munication protocols",
      "frequency": 2,
      "relevance_score": 0.5768420346262246,
      "source_papers": [
        "local/ACRIC__Securing_Legacy_Communication_Networks_via_Authenticated_Cyclic_Redundancy_Integrity_Check"
      ],
      "source_domain": "medical_device_cybersecurity",
      "extraction_method": "tfidf",
      "created_at": "2025-08-07T16:13:34.358816+00:00",
      "synonyms": []
    },
    {
      "text": "legacy systems",
      "frequency": 14,
      "relevance_score": 0.5378942423835726,
      "source_papers": [
        "local/ACRIC__Securing_Legacy_Communication_Networks_via_Authenticated_Cyclic_Redundancy_Integrity_Check"
      ],
      "source_domain": "medical_device_cybersecurity",
      "extraction_method": "tfidf",
      "created_at": "2025-08-07T16:13:34.286083+00:00",
      "synonyms": []
    },
    {
      "text": "hash",
      "frequency": 31,
      "relevance_score": 0.5160515367064824,
      "source_papers": [
        "local/ACRIC__Securing_Legacy_Communication_Networks_via_Authenticated_Cyclic_Redundancy_Integrity_Check"
      ],
      "source_domain": "medical_device_cybersecurity",
      "extraction_method": "tfidf",
      "created_at": "2025-08-07T16:13:34.200175+00:00",
      "synonyms": []
    },
    {
      "text": "industrial control system",
      "frequency": 4,
      "relevance_score": 0.5036840692524494,
      "source_papers": [
        "local/ACRIC__Securing_Legacy_Communication_Networks_via_Authenticated_Cyclic_Redundancy_Integrity_Check"
      ],
      "source_domain": "medical_device_cybersecurity",
      "extraction_method": "tfidf",
      "created_at": "2025-08-07T16:13:34.357933+00:00",
      "synonyms": []
    },
    {
      "text": "industrial control systems",
      "frequency": 4,
      "relevance_score": 0.5036840692524494,
      "source_papers": [
        "local/ACRIC__Securing_Legacy_Communication_Networks_via_Authenticated_Cyclic_Redundancy_Integrity_Check"
      ],
      "source_domain": "medical_device_cybersecurity",
      "extraction_method": "tfidf",
      "created_at": "2025-08-07T16:13:34.372138+00:00",
      "synonyms": []
    },
    {
      "text": "devices",
      "frequency": 30,
      "relevance_score": 0.50263051939337,
      "source_papers": [
        "local/ACRIC__Securing_Legacy_Communication_Networks_via_Authenticated_Cyclic_Redundancy_Integrity_Check"
      ],
      "source_domain": "medical_device_cybersecurity",
      "extraction_method": "tfidf",
      "created_at": "2025-08-07T16:13:34.138120+00:00",
      "synonyms": []
    },
    {
      "text": "industrial communication protocols",
      "frequency": 3,
      "relevance_score": 0.49026305193933695,
      "source_papers": [
        "local/ACRIC__Securing_Legacy_Communication_Networks_via_Authenticated_Cyclic_Redundancy_Integrity_Check"
      ],
      "source_domain": "medical_device_cybersecurity",
      "extraction_method": "tfidf",
      "created_at": "2025-08-07T16:13:34.356829+00:00",
      "synonyms": []
    },
    {
      "text": "integrity",
      "frequency": 29,
      "relevance_score": 0.4892095020802577,
      "source_papers": [
        "local/ACRIC__Securing_Legacy_Communication_Networks_via_Authenticated_Cyclic_Redundancy_Integrity_Check"
      ],
      "source_domain": "medical_device_cybersecurity",
      "extraction_method": "tfidf",
      "created_at": "2025-08-07T16:13:34.131949+00:00",
      "synonyms": []
    },
    {
      "text": "cyclic redundancy integrity",
      "frequency": 14,
      "relevance_score": 0.48789424238357265,
      "source_papers": [
        "local/ACRIC__Securing_Legacy_Communication_Networks_via_Authenticated_Cyclic_Redundancy_Integrity_Check"
      ],
      "source_domain": "medical_device_cybersecurity",
      "extraction_method": "tfidf",
      "created_at": "2025-08-07T16:13:34.355691+00:00",
      "synonyms": []
    },
    {
      "text": "redundancy integrity check",
      "frequency": 14,
      "relevance_score": 0.48789424238357265,
      "source_papers": [
        "local/ACRIC__Securing_Legacy_Communication_Networks_via_Authenticated_Cyclic_Redundancy_Integrity_Check"
      ],
      "source_domain": "medical_device_cybersecurity",
      "extraction_method": "tfidf",
      "created_at": "2025-08-07T16:13:34.355913+00:00",
      "synonyms": []
    },
    {
      "text": "a1 b2 b1",
      "frequency": 6,
      "relevance_score": 0.480526103878674,
      "source_papers": [
        "local/ACRIC__Securing_Legacy_Communication_Networks_via_Authenticated_Cyclic_Redundancy_Integrity_Check"
      ],
      "source_domain": "medical_device_cybersecurity",
      "extraction_method": "tfidf",
      "created_at": "2025-08-07T16:13:34.365667+00:00",
      "synonyms": []
    },
    {
      "text": "f a2 f",
      "frequency": 6,
      "relevance_score": 0.480526103878674,
      "source_papers": [
        "local/ACRIC__Securing_Legacy_Communication_Networks_via_Authenticated_Cyclic_Redundancy_Integrity_Check"
      ],
      "source_domain": "medical_device_cybersecurity",
      "extraction_method": "tfidf",
      "created_at": "2025-08-07T16:13:34.368112+00:00",
      "synonyms": []
    },
    {
      "text": "a2 f a1",
      "frequency": 6,
      "relevance_score": 0.480526103878674,
      "source_papers": [
        "local/ACRIC__Securing_Legacy_Communication_Networks_via_Authenticated_Cyclic_Redundancy_Integrity_Check"
      ],
      "source_domain": "medical_device_cybersecurity",
      "extraction_method": "tfidf",
      "created_at": "2025-08-07T16:13:34.368337+00:00",
      "synonyms": []
    },
    {
      "text": "cyber-physical systems",
      "frequency": 2,
      "relevance_score": 0.47684203462622465,
      "source_papers": [
        "local/ACRIC__Securing_Legacy_Communication_Networks_via_Authenticated_Cyclic_Redundancy_Integrity_Check"
      ],
      "source_domain": "medical_device_cybersecurity",
      "extraction_method": "tfidf",
      "created_at": "2025-08-07T16:13:34.295988+00:00",
      "synonyms": []
    },
    {
      "text": "securing legacy systems",
      "frequency": 2,
      "relevance_score": 0.47684203462622465,
      "source_papers": [
        "local/ACRIC__Securing_Legacy_Communication_Networks_via_Authenticated_Cyclic_Redundancy_Integrity_Check"
      ],
      "source_domain": "medical_device_cybersecurity",
      "extraction_method": "tfidf",
      "created_at": "2025-08-07T16:13:34.359919+00:00",
      "synonyms": []
    },
    {
      "text": "legacy communication protocols",
      "frequency": 2,
      "relevance_score": 0.47684203462622465,
      "source_papers": [
        "local/ACRIC__Securing_Legacy_Communication_Networks_via_Authenticated_Cyclic_Redundancy_Integrity_Check"
      ],
      "source_domain": "medical_device_cybersecurity",
      "extraction_method": "tfidf",
      "created_at": "2025-08-07T16:13:34.361262+00:00",
      "synonyms": []
    },
    {
      "text": "legacy industrial protocols",
      "frequency": 2,
      "relevance_score": 0.47684203462622465,
      "source_papers": [
        "local/ACRIC__Securing_Legacy_Communication_Networks_via_Authenticated_Cyclic_Redundancy_Integrity_Check"
      ],
      "source_domain": "medical_device_cybersecurity",
      "extraction_method": "tfidf",
      "created_at": "2025-08-07T16:13:34.362240+00:00",
      "synonyms": []
    },
    {
      "text": "communication protocols",
      "frequency": 9,
      "relevance_score": 0.47078915581801106,
      "source_papers": [
        "local/ACRIC__Securing_Legacy_Communication_Networks_via_Authenticated_Cyclic_Redundancy_Integrity_Check"
      ],
      "source_domain": "medical_device_cybersecurity",
      "extraction_method": "tfidf",
      "created_at": "2025-08-07T16:13:34.289321+00:00",
      "synonyms": []
    },
    {
      "text": "authenticated cyclic redundancy",
      "frequency": 12,
      "relevance_score": 0.461052207757348,
      "source_papers": [
        "local/ACRIC__Securing_Legacy_Communication_Networks_via_Authenticated_Cyclic_Redundancy_Integrity_Check"
      ],
      "source_domain": "medical_device_cybersecurity",
      "extraction_method": "tfidf",
      "created_at": "2025-08-07T16:13:34.355470+00:00",
      "synonyms": []
    },
    {
      "text": "a1 b1 c1",
      "frequency": 4,
      "relevance_score": 0.4536840692524493,
      "source_papers": [
        "local/ACRIC__Securing_Legacy_Communication_Networks_via_Authenticated_Cyclic_Redundancy_Integrity_Check"
      ],
      "source_domain": "medical_device_cybersecurity",
      "extraction_method": "tfidf",
      "created_at": "2025-08-07T16:13:34.365196+00:00",
      "synonyms": []
    },
    {
      "text": "a2 a1 b2",
      "frequency": 4,
      "relevance_score": 0.4536840692524493,
      "source_papers": [
        "local/ACRIC__Securing_Legacy_Communication_Networks_via_Authenticated_Cyclic_Redundancy_Integrity_Check"
      ],
      "source_domain": "medical_device_cybersecurity",
      "extraction_method": "tfidf",
      "created_at": "2025-08-07T16:13:34.365416+00:00",
      "synonyms": []
    },
    {
      "text": "f a1 b1",
      "frequency": 4,
      "relevance_score": 0.4536840692524493,
      "source_papers": [
        "local/ACRIC__Securing_Legacy_Communication_Networks_via_Authenticated_Cyclic_Redundancy_Integrity_Check"
      ],
      "source_domain": "medical_device_cybersecurity",
      "extraction_method": "tfidf",
      "created_at": "2025-08-07T16:13:34.366930+00:00",
      "synonyms": []
    },
    {
      "text": "initvec",
      "frequency": 26,
      "relevance_score": 0.4489464501409207,
      "source_papers": [
        "local/ACRIC__Securing_Legacy_Communication_Networks_via_Authenticated_Cyclic_Redundancy_Integrity_Check"
      ],
      "source_domain": "medical_device_cybersecurity",
      "extraction_method": "tfidf",
      "created_at": "2025-08-07T16:13:34.208674+00:00",
      "synonyms": []
    },
    {
      "text": "f a1",
      "frequency": 11,
      "relevance_score": 0.4476311904442357,
      "source_papers": [
        "local/ACRIC__Securing_Legacy_Communication_Networks_via_Authenticated_Cyclic_Redundancy_Integrity_Check"
      ],
      "source_domain": "medical_device_cybersecurity",
      "extraction_method": "tfidf",
      "created_at": "2025-08-07T16:13:34.332040+00:00",
      "synonyms": []
    },
    {
      "text": "cyclic redundancy",
      "frequency": 18,
      "relevance_score": 0.441578311636022,
      "source_papers": [
        "local/ACRIC__Securing_Legacy_Communication_Networks_via_Authenticated_Cyclic_Redundancy_Integrity_Check"
      ],
      "source_domain": "medical_device_cybersecurity",
      "extraction_method": "tfidf",
      "created_at": "2025-08-07T16:13:34.282931+00:00",
      "synonyms": []
    },
    {
      "text": "b2 b1 having",
      "frequency": 3,
      "relevance_score": 0.440263051939337,
      "source_papers": [
        "local/ACRIC__Securing_Legacy_Communication_Networks_via_Authenticated_Cyclic_Redundancy_Integrity_Check"
      ],
      "source_domain": "medical_device_cybersecurity",
      "extraction_method": "tfidf",
      "created_at": "2025-08-07T16:13:34.365930+00:00",
      "synonyms": []
    },
    {
      "text": "collision c2 f",
      "frequency": 3,
      "relevance_score": 0.440263051939337,
      "source_papers": [
        "local/ACRIC__Securing_Legacy_Communication_Networks_via_Authenticated_Cyclic_Redundancy_Integrity_Check"
      ],
      "source_domain": "medical_device_cybersecurity",
      "extraction_method": "tfidf",
      "created_at": "2025-08-07T16:13:34.366160+00:00",
      "synonyms": []
    },
    {
      "text": "f a1 b2",
      "frequency": 3,
      "relevance_score": 0.440263051939337,
      "source_papers": [
        "local/ACRIC__Securing_Legacy_Communication_Networks_via_Authenticated_Cyclic_Redundancy_Integrity_Check"
      ],
      "source_domain": "medical_device_cybersecurity",
      "extraction_method": "tfidf",
      "created_at": "2025-08-07T16:13:34.366411+00:00",
      "synonyms": []
    },
    {
      "text": "b1 c1 implies",
      "frequency": 3,
      "relevance_score": 0.440263051939337,
      "source_papers": [
        "local/ACRIC__Securing_Legacy_Communication_Networks_via_Authenticated_Cyclic_Redundancy_Integrity_Check"
      ],
      "source_domain": "medical_device_cybersecurity",
      "extraction_method": "tfidf",
      "created_at": "2025-08-07T16:13:34.367202+00:00",
      "synonyms": []
    },
    {
      "text": "pr c2 c1",
      "frequency": 3,
      "relevance_score": 0.440263051939337,
      "source_papers": [
        "local/ACRIC__Securing_Legacy_Communication_Networks_via_Authenticated_Cyclic_Redundancy_Integrity_Check"
      ],
      "source_domain": "medical_device_cybersecurity",
      "extraction_method": "tfidf",
      "created_at": "2025-08-07T16:13:34.367671+00:00",
      "synonyms": []
    },
    {
      "text": "m 1 2n",
      "frequency": 3,
      "relevance_score": 0.440263051939337,
      "source_papers": [
        "local/ACRIC__Securing_Legacy_Communication_Networks_via_Authenticated_Cyclic_Redundancy_Integrity_Check"
      ],
      "source_domain": "medical_device_cybersecurity",
      "extraction_method": "tfidf",
      "created_at": "2025-08-07T16:13:34.369036+00:00",
      "synonyms": []
    },
    {
      "text": "control systems",
      "frequency": 6,
      "relevance_score": 0.43052610387867396,
      "source_papers": [
        "local/ACRIC__Securing_Legacy_Communication_Networks_via_Authenticated_Cyclic_Redundancy_Integrity_Check"
      ],
      "source_domain": "medical_device_cybersecurity",
      "extraction_method": "tfidf",
      "created_at": "2025-08-07T16:13:34.317827+00:00",
      "synonyms": []
    },
    {
      "text": "acric s",
      "frequency": 17,
      "relevance_score": 0.4281572943229097,
      "source_papers": [
        "local/ACRIC__Securing_Legacy_Communication_Networks_via_Authenticated_Cyclic_Redundancy_Integrity_Check"
      ],
      "source_domain": "medical_device_cybersecurity",
      "extraction_method": "tfidf",
      "created_at": "2025-08-07T16:13:34.290963+00:00",
      "synonyms": []
    },
    {
      "text": "hash chain",
      "frequency": 17,
      "relevance_score": 0.4281572943229097,
      "source_papers": [
        "local/ACRIC__Securing_Legacy_Communication_Networks_via_Authenticated_Cyclic_Redundancy_Integrity_Check"
      ],
      "source_domain": "medical_device_cybersecurity",
      "extraction_method": "tfidf",
      "created_at": "2025-08-07T16:13:34.320064+00:00",
      "synonyms": []
    },
    {
      "text": "authen- ticated cyclic",
      "frequency": 2,
      "relevance_score": 0.4268420346262246,
      "source_papers": [
        "local/ACRIC__Securing_Legacy_Communication_Networks_via_Authenticated_Cyclic_Redundancy_Integrity_Check"
      ],
      "source_domain": "medical_device_cybersecurity",
      "extraction_method": "tfidf",
      "created_at": "2025-08-07T16:13:34.358152+00:00",
      "synonyms": []
    },
    {
      "text": "message au- thentication",
      "frequency": 2,
      "relevance_score": 0.4268420346262246,
      "source_papers": [
        "local/ACRIC__Securing_Legacy_Communication_Networks_via_Authenticated_Cyclic_Redundancy_Integrity_Check"
      ],
      "source_domain": "medical_device_cybersecurity",
      "extraction_method": "tfidf",
      "created_at": "2025-08-07T16:13:34.360139+00:00",
      "synonyms": []
    },
    {
      "text": "ks 0 ks",
      "frequency": 2,
      "relevance_score": 0.4268420346262246,
      "source_papers": [
        "local/ACRIC__Securing_Legacy_Communication_Networks_via_Authenticated_Cyclic_Redundancy_Integrity_Check"
      ],
      "source_domain": "medical_device_cybersecurity",
      "extraction_method": "tfidf",
      "created_at": "2025-08-07T16:13:34.362957+00:00",
      "synonyms": []
    },
    {
      "text": "cryptographic pa- rameters",
      "frequency": 2,
      "relevance_score": 0.4268420346262246,
      "source_papers": [
        "local/ACRIC__Securing_Legacy_Communication_Networks_via_Authenticated_Cyclic_Redundancy_Integrity_Check"
      ],
      "source_domain": "medical_device_cybersecurity",
      "extraction_method": "tfidf",
      "created_at": "2025-08-07T16:13:34.363400+00:00",
      "synonyms": []
    },
    {
      "text": "pair group -",
      "frequency": 2,
      "relevance_score": 0.4268420346262246,
      "source_papers": [
        "local/ACRIC__Securing_Legacy_Communication_Networks_via_Authenticated_Cyclic_Redundancy_Integrity_Check"
      ],
      "source_domain": "medical_device_cybersecurity",
      "extraction_method": "tfidf",
      "created_at": "2025-08-07T16:13:34.364305+00:00",
      "synonyms": []
    },
    {
      "text": "b2 f a1",
      "frequency": 2,
      "relevance_score": 0.4268420346262246,
      "source_papers": [
        "local/ACRIC__Securing_Legacy_Communication_Networks_via_Authenticated_Cyclic_Redundancy_Integrity_Check"
      ],
      "source_domain": "medical_device_cybersecurity",
      "extraction_method": "tfidf",
      "created_at": "2025-08-07T16:13:34.366656+00:00",
      "synonyms": []
    }
  ],
  "extraction_timestamp": "2025-08-07T16:13:34.380335+00:00",
  "extraction_method": "mixed",
  "total_concept_count": 50,
  "processing_metadata": {
    "strategies_used": [
      "tfidf"
    ],
    "total_concepts_found": 50,
    "concepts_after_consolidation": 50,
    "concepts_after_filtering": 50
  },
  "_metadata": {
    "saved_at": "2025-08-07T16:13:34.380580+00:00",
    "repository_version": "1.0",
    "domain": "medical_device_cybersecurity"
  }
}